{
  "id": "1190ecfa-062d-40b4-a909-3d3e06fb3556",
  "prevId": "00000000-0000-0000-0000-000000000000",
  "version": "7",
  "dialect": "postgresql",
  "tables": {
    "benchmarks.snapshots": {
      "name": "snapshots",
      "schema": "benchmarks",
      "columns": {
        "id": {
          "name": "id",
          "type": "uuid",
          "primaryKey": true,
          "notNull": true,
          "default": "gen_random_uuid()"
        },
        "facility_id": {
          "name": "facility_id",
          "type": "text",
          "primaryKey": false,
          "notNull": true
        },
        "facility_name": {
          "name": "facility_name",
          "type": "text",
          "primaryKey": false,
          "notNull": true
        },
        "reservation_url": {
          "name": "reservation_url",
          "type": "text",
          "primaryKey": false,
          "notNull": true
        },
        "scraped_at": {
          "name": "scraped_at",
          "type": "timestamp with time zone",
          "primaryKey": false,
          "notNull": true,
          "default": "now()"
        },
        "date_checked": {
          "name": "date_checked",
          "type": "date",
          "primaryKey": false,
          "notNull": true
        },
        "time_slot": {
          "name": "time_slot",
          "type": "time",
          "primaryKey": false,
          "notNull": true
        },
        "court_id": {
          "name": "court_id",
          "type": "text",
          "primaryKey": false,
          "notNull": true
        },
        "is_available": {
          "name": "is_available",
          "type": "boolean",
          "primaryKey": false,
          "notNull": true
        },
        "raw_payload": {
          "name": "raw_payload",
          "type": "jsonb",
          "primaryKey": false,
          "notNull": false
        },
        "created_at": {
          "name": "created_at",
          "type": "timestamp with time zone",
          "primaryKey": false,
          "notNull": true,
          "default": "now()"
        }
      },
      "indexes": {
        "idx_snap_facility_date": {
          "name": "idx_snap_facility_date",
          "columns": [
            {
              "expression": "facility_id",
              "isExpression": false,
              "asc": true,
              "nulls": "last"
            },
            {
              "expression": "date_checked",
              "isExpression": false,
              "asc": true,
              "nulls": "last"
            }
          ],
          "isUnique": false,
          "concurrently": false,
          "method": "btree",
          "with": {}
        },
        "idx_snap_scraped_at": {
          "name": "idx_snap_scraped_at",
          "columns": [
            {
              "expression": "scraped_at",
              "isExpression": false,
              "asc": true,
              "nulls": "last"
            }
          ],
          "isUnique": false,
          "concurrently": false,
          "method": "btree",
          "with": {}
        }
      },
      "foreignKeys": {},
      "compositePrimaryKeys": {},
      "uniqueConstraints": {},
      "policies": {},
      "checkConstraints": {},
      "isRLSEnabled": false
    },
    "benchmarks.scrape_runs": {
      "name": "scrape_runs",
      "schema": "benchmarks",
      "columns": {
        "id": {
          "name": "id",
          "type": "uuid",
          "primaryKey": true,
          "notNull": true,
          "default": "gen_random_uuid()"
        },
        "started_at": {
          "name": "started_at",
          "type": "timestamp with time zone",
          "primaryKey": false,
          "notNull": true
        },
        "finished_at": {
          "name": "finished_at",
          "type": "timestamp with time zone",
          "primaryKey": false,
          "notNull": false
        },
        "facilities_total": {
          "name": "facilities_total",
          "type": "integer",
          "primaryKey": false,
          "notNull": true
        },
        "facilities_ok": {
          "name": "facilities_ok",
          "type": "integer",
          "primaryKey": false,
          "notNull": true
        },
        "facilities_failed": {
          "name": "facilities_failed",
          "type": "integer",
          "primaryKey": false,
          "notNull": true
        },
        "snapshots_written": {
          "name": "snapshots_written",
          "type": "integer",
          "primaryKey": false,
          "notNull": true
        },
        "validation_status": {
          "name": "validation_status",
          "type": "text",
          "primaryKey": false,
          "notNull": true
        },
        "validation_notes": {
          "name": "validation_notes",
          "type": "text",
          "primaryKey": false,
          "notNull": false
        },
        "report_json": {
          "name": "report_json",
          "type": "jsonb",
          "primaryKey": false,
          "notNull": true
        }
      },
      "indexes": {},
      "foreignKeys": {},
      "compositePrimaryKeys": {},
      "uniqueConstraints": {},
      "policies": {},
      "checkConstraints": {},
      "isRLSEnabled": false
    }
  },
  "enums": {
    "public.validation_status": {
      "name": "validation_status",
      "schema": "public",
      "values": [
        "ok",
        "anomaly",
        "fail"
      ]
    }
  },
  "schemas": {
    "benchmarks": "benchmarks"
  },
  "sequences": {},
  "roles": {},
  "policies": {},
  "views": {},
  "_meta": {
    "columns": {},
    "schemas": {},
    "tables": {}
  }
}